steal_douyin_video_content_url/__init__.py
steal_douyin_video_content_url/exception.py
steal_douyin_video_content_url/render_data_object_strategy.py
steal_douyin_video_content_url/steal_douyin_video_content_url.py
steal_douyin_video_content_url-0.7.dist-info/LICENSE
steal_douyin_video_content_url-0.7.dist-info/METADATA
steal_douyin_video_content_url-0.7.dist-info/WHEEL
steal_douyin_video_content_url-0.7.dist-info/entry_points.txt
steal_douyin_video_content_url-0.7.dist-info/top_level.txt
steal_douyin_video_content_url-0.7.dist-info/RECORD
