Metadata-Version: 2.1
Name: steal_douyin_video_content_url
Version: 0.7
Summary: Steal douyin.com video content url
Home-page: https://github.com/FredericDT/steal-douyin-video-content-url
License: GPLv3 License
Keywords: douyin,video,url
Classifier: Programming Language :: Python :: 3
License-File: LICENSE
Requires-Dist: beautifulsoup4 ==4.11.1
Requires-Dist: requests ==2.28.1
Requires-Dist: urllib3 ==1.26.13
